ovos_yaml_editor/__init__.py
ovos_yaml_editor/version.py
ovos_yaml_editor-0.0.2.dist-info/LICENSE
ovos_yaml_editor-0.0.2.dist-info/METADATA
ovos_yaml_editor-0.0.2.dist-info/WHEEL
ovos_yaml_editor-0.0.2.dist-info/entry_points.txt
ovos_yaml_editor-0.0.2.dist-info/top_level.txt
ovos_yaml_editor-0.0.2.dist-info/RECORD
